Lab-05/comparator_2bit_f.vhd
library IEEE;
use IEEE.STD_LOGIC_1164.ALL;
entity comparator_2bit_f is
    Port ( A   : in  STD_LOGIC_VECTOR (1 downto 0);
           B   : in  STD_LOGIC_VECTOR (1 downto 0);
           greater : out STD_LOGIC;
           equal   : out STD_LOGIC;
           less    : out STD_LOGIC);
end comparator_2bit_f;
architecture Dataflow of comparator_2bit_f is
begin
    greater <= '1' when (A > B) else '0';
    equal   <= '1' when (A = B) else '0';
    less    <= '1' when (A < B) else '0';
end Dataflow;

Lab-05/comparator_2bit_f_tb.vhd
library IEEE;
use IEEE.STD_LOGIC_1164.ALL;
use IEEE.NUMERIC_STD.ALL; -- Necessary for the to_unsigned conversion loops

entity comparator_2bit_f_tb is
-- Testbenches do not have input/output ports
end comparator_2bit_f_tb;

architecture Behavioral of comparator_2bit_f_tb is

    -- Component Declaration for the Unit Under Test (UUT)
    component comparator_2bit_f
        Port ( A       : in  STD_LOGIC_VECTOR (1 downto 0);
               B       : in  STD_LOGIC_VECTOR (1 downto 0);
               greater : out STD_LOGIC;
               equal   : out STD_LOGIC;
               less    : out STD_LOGIC);
    end component;
    
    -- Signals to connect to the UUT
    signal A_tb       : STD_LOGIC_VECTOR(1 downto 0) := "00";
    signal B_tb       : STD_LOGIC_VECTOR(1 downto 0) := "00";
    signal greater_tb : STD_LOGIC;
    signal equal_tb   : STD_LOGIC;
    signal less_tb    : STD_LOGIC;

begin

    -- Instantiate the Unit Under Test (UUT)
    uut: comparator_2bit_f PORT MAP (
          A       => A_tb,
          B       => B_tb,
          greater => greater_tb,
          equal   => equal_tb,
          less    => less_tb
        );

    -- Stimulus process to step through all input combinations
    stim_proc: process
    begin		
        -- Nested loops to test all 16 states (A: 0-3, B: 0-3)
        for i in 0 to 3 loop
            for j in 0 to 3 loop
                A_tb <= std_logic_vector(to_unsigned(i, 2));
                B_tb <= std_logic_vector(to_unsigned(j, 2));
                wait for 10 ns; -- Holds state for 10ns in the waveform
            end loop;
        end loop;

        -- Suspend the process indefinitely so simulation doesn't loop
        wait;
    end process;

end Behavioral;

Lab-05/waveform_f.vcd
$date
  Tue Jun 23 09:28:27 2026
$end
$version
  GHDL v0
$end
$timescale
  1 fs
$end
$scope module standard $end
$upscope $end
$scope module std_logic_1164 $end
$upscope $end
$scope module numeric_std $end
$upscope $end
$scope module comparator_2bit_f_tb $end
$var reg 2 ! a_tb[1:0] $end
$var reg 2 " b_tb[1:0] $end
$var reg 1 # greater_tb $end
$var reg 1 $ equal_tb $end
$var reg 1 % less_tb $end
$scope module uut $end
$var reg 2 & a[1:0] $end
$var reg 2 ' b[1:0] $end
$var reg 1 ( greater $end
$var reg 1 ) equal $end
$var reg 1 * less $end
$upscope $end
$upscope $end
$enddefinitions $end
#0
b00 !
b00 "
0#
1$
0%
b00 &
b00 '
0(
1)
0*
#10000000
b01 "
0$
1%
b01 '
0)
1*
#20000000
b10 "
b10 '
#30000000
b11 "
b11 '
#40000000
b01 !
b00 "
1#
0%
b01 &
b00 '
1(
0*
#50000000
b01 "
0#
1$
b01 '
0(
1)
#60000000
b10 "
0$
1%
b10 '
0)
1*
#70000000
b11 "
b11 '
#80000000
b10 !
b00 "
1#
0%
b10 &
b00 '
1(
0*
#90000000
b01 "
b01 '
#100000000
b10 "
0#
1$
b10 '
0(
1)
#110000000
b11 "
0$
1%
b11 '
0)
1*
#120000000
b11 !
b00 "
1#
0%
b11 &
b00 '
1(
0*
#130000000
b01 "
b01 '
#140000000
b10 "
b10 '
#150000000
b11 "
0#
1$
b11 '
0(
1)
